pywordsegment-0.4.3.dist-info/METADATA
pywordsegment-0.4.3.dist-info/WHEEL
pywordsegment/bigrams.msgpack.gz
pywordsegment/pywordsegment.pyi
pywordsegment/unigrams.msgpack.gz
pywordsegment/__init__.py
pywordsegment/pywordsegment.cp39-win_amd64.pyd
pywordsegment-0.4.3.dist-info/RECORD
