Metadata-Version: 2.1
Name: pywordsegment
Version: 0.4.3
Summary: Concatenated-word segmentation Python library written in Rust
Keywords: word,segment,rust,pyo3
Home-Page: https://github.com/intsights/pywordsegment
Author: Gal Ben David <gal@intsights.com>
Author-email: Gal Ben David <gal@intsights.com>
License: MIT
Project-URL: Source Code, https://github.com/intsights/pywordsegment
